[
  { "zhongwen": "我叫张明", "pinyin1": "", "english": ["I am Zhang Ming"] },
  { "zhongwen": "叫我张", "pinyin1": "", "english": ["Call me Zhang"] },
  { "zhongwen": "叫我李", "pinyin1": "", "english": ["Call me Li"] },
  { "zhongwen": "叫我李华", "pinyin1": "", "english": ["Call me Li Hua"] },
  { "zhongwen": "你叫王华吗？", "pinyin1": "", "english": ["Are you Wang Hua?"] },
  { "zhongwen": "我叫李明", "pinyin1": "", "english": ["My name is Li Ming"] },
  { "zhongwen": "我叫李明，你呢？", "pinyin1": "", "english": ["My name is Li Ming, what's yours?"] },
  { "zhongwen": "你叫明", "pinyin1": "", "english": ["Your name is Ming"] },
  { "zhongwen": "我姓明", "pinyin1": "", "english": ["My last name is Ming"] },
  { "zhongwen": "我姓王，你呢？", "pinyin1": "", "english": ["My last name is Wang, what's yours?"] },
  { "zhongwen": "我姓王，我叫王明", "pinyin1": "", "english": ["My last name is Wang, my name is Wang Ming"] },
  { "zhongwen": "你姓张", "pinyin1": "", "english": ["Your last name is Zhang"] },
  { "zhongwen": "我叫李华，你叫什么？", "pinyin1": "", "english": ["My name is Li Hua, what's your name?"] },
  { "zhongwen": "你姓李，我姓王", "pinyin1": "", "english": ["Your last name is Li, my last name is Wang"] },
  { "zhongwen": "他姓李", "pinyin1": "", "english": ["His last name is Li"] },
  { "zhongwen": "他姓李，对吗？", "pinyin1": "", "english": ["His last name is Li, right?"] },
  { "zhongwen": "你叫什么？", "pinyin1": "", "english": ["What is your name?"] },
  { "zhongwen": "你姓什么？", "pinyin1": "", "english": ["What is your last name?"] },
  { "zhongwen": "她叫什么？", "pinyin1": "", "english": ["What is her name?"] },
  { "zhongwen": "老师姓什么？", "pinyin1": "", "english": ["What is the teacher's last name?"] },
  { "zhongwen": "我也叫王", "pinyin1": "", "english": ["My name is also Wang"] },
  { "zhongwen": "我也姓李", "pinyin1": "", "english": ["My last name is also Li"] },
  { "zhongwen": "我名字叫明", "pinyin1": "", "english": ["My first name is Ming"] },
  { "zhongwen": "她名字叫李", "pinyin1": "", "english": ["Her first name is Li"] },
  { "zhongwen": "你名字叫华吗？", "pinyin1": "", "english": ["Is your first name Hua?"] },
  { "zhongwen": "我们不姓王", "pinyin1": "", "english": ["Our last name isn't Wang"] },
  { "zhongwen": "你好！", "pinyin1": "", "english": ["Hi!"] },
  { "zhongwen": "再见！", "pinyin1": "", "english": ["Bye!"] },
  { "zhongwen": "我很高兴", "pinyin1": "", "english": ["I am happy"] },
  { "zhongwen": "我很高兴，你呢？", "pinyin1": "", "english": ["I am happy, how about you?"] },
  { "zhongwen": "你很高兴吗？", "pinyin1": "", "english": ["Are you happy?"] },
  { "zhongwen": "他们很高兴吗？", "pinyin1": "", "english": ["Are they happy?"] },
  { "zhongwen": "他也很高兴", "pinyin1": "", "english": ["She is also happy"] },
  { "zhongwen": "他不高兴", "pinyin1": "", "english": ["He is not happy"] },
  { "zhongwen": "很高兴认识你", "pinyin1": "", "english": ["Nice to meet you"] },
  { "zhongwen": "我也很高兴认识你", "pinyin1": "", "english": ["Nice to meet you too"] },
  { "zhongwen": "我认识你", "pinyin1": "", "english": ["I know you"] },
  { "zhongwen": "我认识张明", "pinyin1": "", "english": ["I know Zhang Ming"] },
  { "zhongwen": "我认识你，你叫李明", "pinyin1": "", "english": ["I know you, you are Li Ming"] },
  { "zhongwen": "我认识他", "pinyin1": "", "english": ["I know him"] },
  { "zhongwen": "你认识王华吗？", "pinyin1": "", "english": ["Do you know Wang Hua?"] },
  { "zhongwen": "你认识她吗？", "pinyin1": "", "english": ["Do you know her?"] },
  { "zhongwen": "你认识他，对吗？", "pinyin1": "", "english": ["You know him, right?"] },
  { "zhongwen": "你认识他们吗？", "pinyin1": "", "english": ["Do you know them?"] },
  { "zhongwen": "他们认识你", "pinyin1": "", "english": ["They know you"] },
  { "zhongwen": "他们认识你吗？", "pinyin1": "", "english": ["Do they know you?"] },
  { "zhongwen": "谢谢", "pinyin1": "", "english": ["Thank you"] },
  { "zhongwen": "我吃面", "pinyin1": "", "english": ["I eat noodles"] },
  { "zhongwen": "我吃饭，你呢？", "pinyin1": "", "english": ["I eat rice, what about you?"] },
  { "zhongwen": "我们不吃鱼", "pinyin1": "", "english": ["We do not eat fish"] },
  { "zhongwen": "他们吃饭", "pinyin1": "", "english": ["They eat rice"] },
  { "zhongwen": "你吃面吗？", "pinyin1": "", "english": ["Do you eat noodles?"] },
  { "zhongwen": "你吃鱼吗？", "pinyin1": "", "english": ["Do you eat fish?"] },
  { "zhongwen": "他们吃鱼吗？", "pinyin1": "", "english": ["Do they eat fish?"] },
  { "zhongwen": "张明吃饭，你吃什么？", "pinyin1": "", "english": ["Zhang Ming eats rice, what do you eat?"] },
  { "zhongwen": "我喝水", "pinyin1": "", "english": ["I drink water"] },
  { "zhongwen": "我也不喝茶", "pinyin1": "", "english": ["I don't drink tea either"] },
  { "zhongwen": "我是学生", "pinyin1": "", "english": ["I am a student"] },
  { "zhongwen": "我是学生，你呢？", "pinyin1": "", "english": ["I am a student, what about you?"] },
  { "zhongwen": "你是医生吗？", "pinyin1": "", "english": ["Are you a doctor?"] },
  { "zhongwen": "你们是学生吗？", "pinyin1": "", "english": ["Are you students?"] },
  { "zhongwen": "她是医生", "pinyin1": "", "english": ["She is a doctor"] },
  { "zhongwen": "她也是医生", "pinyin1": "", "english": ["She is also a doctor"] },
  { "zhongwen": "她是老师吗？", "pinyin1": "", "english": ["Is she a teacher?"] },
  { "zhongwen": "他们是医生", "pinyin1": "", "english": ["They are doctors"] },
  { "zhongwen": "他们不是学生", "pinyin1": "", "english": ["They aren't students"] },
  { "zhongwen": "他们是学生吗？", "pinyin1": "", "english": ["Are they students?"] },
  { "zhongwen": "他们不是学生吗？", "pinyin1": "", "english": ["Aren't they students?"] },
  { "zhongwen": "我们是学生", "pinyin1": "", "english": ["We are students"] },
  { "zhongwen": "我是中国人", "pinyin1": "", "english": ["I am Chinese"] },
  { "zhongwen": "我们都是英国人", "pinyin1": "", "english": ["We are all British"] },
  { "zhongwen": "对，我是英国人", "pinyin1": "", "english": ["Yes, I am British"] },
  { "zhongwen": "你是哪国人？", "pinyin1": "", "english": ["Which country are you from?"] },
  { "zhongwen": "你是中国人吗？", "pinyin1": "", "english": ["Are you Chinese?"] },
  { "zhongwen": "你们都是中国人吗？", "pinyin1": "", "english": ["Are you all Chinese?"] },
  { "zhongwen": "你是英国人吗？", "pinyin1": "", "english": ["Are you British?"] },
  { "zhongwen": "你不是英国人吗？", "pinyin1": "", "english": ["Aren't you British?"] },
  { "zhongwen": "你是英国人，对吗？", "pinyin1": "", "english": ["You are British, right?"] },
  { "zhongwen": "他们都是英国人", "pinyin1": "", "english": ["They're all British"] },
  { "zhongwen": "他们都是英国人，你呢？", "pinyin1": "", "english": ["They're all British, what about you?"] },
  { "zhongwen": "他们是加拿大人吗？", "pinyin1": "", "english": ["Are they Canadian?"] },
  { "zhongwen": "她也是加拿大人吗？", "pinyin1": "", "english": ["Is she also Canadian?"] },
  { "zhongwen": "他不是美国人", "pinyin1": "", "english": ["He isn't American"] },
  { "zhongwen": "不对，他不是美国人", "pinyin1": "", "english": ["No, he isn't American"] },
  { "zhongwen": "他们也不是美国人", "pinyin1": "", "english": ["They aren't American either"] },
  { "zhongwen": "王医生是哪国人？", "pinyin1": "", "english": ["Which country is doctor Wang from?"] },
  { "zhongwen": "李老师是英国人", "pinyin1": "", "english": ["Teacher Li is British"] },
  { "zhongwen": "他们都不是美国人", "pinyin1": "", "english": ["None of them are American"] },
  { "zhongwen": "我的电话", "pinyin1": "", "english": ["My phone"] },
  { "zhongwen": "你的电话", "pinyin1": "", "english": ["Your phone"] },
  { "zhongwen": "他的电话", "pinyin1": "", "english": ["His phone"] },
  { "zhongwen": "他的老师的电话", "pinyin1": "", "english": ["His teacher's phone"] },
  { "zhongwen": "你的电话号码是多少？", "pinyin1": "", "english": ["What is your phone number?"] },
  { "zhongwen": "她的电话号码是多少？", "pinyin1": "", "english": ["What is her phone number?"] },
  { "zhongwen": "李老师的电话号码是多少？", "pinyin1": "", "english": ["What is teacher Li's phone number?"] },
  { "zhongwen": "我的电话号码是八六三一六二四三零零八七", "pinyin1": "", "english": ["My phone number is +86-316-2430087"] },
  { "zhongwen": "我的电话号码八六一八一九零八三六零零六", "pinyin1": "", "english": ["My phone number is +86-18190-836006"] },
  { "zhongwen": "我的电话号码是零二零八五八五一四五二", "pinyin1": "", "english": ["My phone number is 020-85851452"] },
  { "zhongwen": "我的电话号码是一五六四三八九三二四三", "pinyin1": "", "english": ["My phone number is 15643-893243"] },
  { "zhongwen": "你的电话号码是零二零八五八五一四五二，对吗？", "pinyin1": "", "english": ["Your phone number is 020-85851452, right?"] },
  { "zhongwen": "你的电话号码是一四七零二三五六二八三吗？", "pinyin1": "", "english": ["Is your phone number 14702-356283?"] },
  { "zhongwen": "你的电话号码是零五一七八四一二五二一一吗？", "pinyin1": "", "english": ["Is your phone number 0517-84125211?"] },
  { "zhongwen": "他的电话号码是零二零八五八五一四五二", "pinyin1": "", "english": ["His phone number is 020-85851452"] },
  { "zhongwen": "她的电话号码是一六四五三三二八九三四吗？", "pinyin1": "", "english": ["Is her phone number 16453-328934?"] }
]
